{
  "voice_id": "v_en_171",
  "display_name": "ChillBestie",
  "source": {
    "provider": "MiniMax",
    "voice_id": "355321486373086",
    "catalog": "中英音色表.md",
    "section": "英文音色",
    "section_index": 95,
    "global_index": 171
  },
  "profile": {
    "gender": "female",
    "age_band": "teen",
    "species": "human",
    "locale": "en-US",
    "language": "英语-美音",
    "accent": "未标注"
  },
  "style_tags": {
    "timbre": [
      "略带沙哑",
      "松弛漫不经心",
      "丧系幽默感"
    ],
    "pace_default": "medium",
    "energy": "low_medium",
    "emotion_bias": [
      "friendly",
      "humorous"
    ]
  },
  "fit_roles": [
    "社媒Vlog旁白",
    "轻松的播客对话或现代都市题材的广播剧",
    "能够完美契合那个不想努力的慵懒少女设定"
  ],
  "constraints": {
    "not_good_for": [],
    "notes": "根据中英音色表自动生成，需用试听音频做最终听感复核。"
  },
  "description": "这是一个慵懒随性的青年女声。其声线略带沙哑和颗粒感，说话节奏松弛漫不经心，伴有自然的停顿和口语化气息。整体风格亲切且带有独特的丧系幽默感，听起来像是一位正在和闺蜜闲聊的死党，非常适合用于社媒Vlog旁白、轻松的播客对话或现代都市题材的广播剧，能够完美契合那个不想努力的慵懒少女设定。",
  "voxcpm2_control": "英语-美音女声，口音：未标注。声音定位：略带沙哑、松弛漫不经心、丧系幽默感。这是一个慵懒随性的青年女声。其声线略带沙哑和颗粒感，说话节奏松弛漫不经心，伴有自然的停顿和口语化气息。整体风格亲切且带有独特的丧系幽默感，听起来像是一位正在和闺蜜闲聊的死党，非常适合用于社媒Vlog旁白、轻松的播客对话或现代都市题材的广播剧，能够完美契合那个不想努力的慵懒少女设定。合成时保持吐字清晰、节奏稳定、角色一致；不要偏离原始声音定位。"
}
