{
  "voice_id": "v_zh_056",
  "display_name": "专业女主持",
  "source": {
    "provider": "MiniMax",
    "voice_id": "226869000163484",
    "catalog": "中英音色表.md",
    "section": "中文音色",
    "section_index": 56,
    "global_index": 56
  },
  "profile": {
    "gender": "female",
    "age_band": "adult",
    "species": "human",
    "locale": "zh-HK",
    "language": "中文-粤语",
    "accent": "标准口音"
  },
  "style_tags": {
    "timbre": [
      "清晰明亮",
      "紧凑流畅",
      "新闻现场感"
    ],
    "pace_default": "medium_fast",
    "energy": "medium",
    "emotion_bias": [
      "serious",
      "professional"
    ]
  },
  "fit_roles": [
    "粤语新闻播报",
    "财经快讯或严肃的社会纪实类节目"
  ],
  "constraints": {
    "not_good_for": [],
    "notes": "根据中英音色表自动生成，需用试听音频做最终听感复核。"
  },
  "description": "这是一个干练专业的女声。其声线清晰明亮且字正腔圆，说话节奏紧凑流畅、掷地有声。整体风格端庄严肃且客观冷静，自带一种强烈的新闻现场感，非常适合用于粤语新闻播报、财经快讯或严肃的社会纪实类节目。",
  "voxcpm2_control": "中文-粤语女声，口音：标准口音。声音定位：清晰明亮、紧凑流畅、新闻现场感。这是一个干练专业的女声。其声线清晰明亮且字正腔圆，说话节奏紧凑流畅、掷地有声。整体风格端庄严肃且客观冷静，自带一种强烈的新闻现场感，非常适合用于粤语新闻播报、财经快讯或严肃的社会纪实类节目。合成时保持吐字清晰、节奏稳定、角色一致；不要偏离原始声音定位。"
}
